README.md
setup.py
chat_mistress.egg-info/PKG-INFO
chat_mistress.egg-info/SOURCES.txt
chat_mistress.egg-info/dependency_links.txt
chat_mistress.egg-info/entry_points.txt
chat_mistress.egg-info/requires.txt
chat_mistress.egg-info/top_level.txt
chatmistress/__init__.py
chatmistress/chatmistress.py
chatmistress/core.py
chatmistress/utils.py
chatmistress/webbot.py
chatmistress/roles/landlady.yml
chatmistress/roles/wife.yml
chatmistress/templates/role_play_summary.txt
chatmistress/templates/role_play_sys.txt