Metadata-Version: 2.1
Name: chat-mistress
Version: 0.7.4
Summary: chat-mistress: 基于GPT3.5的女王聊天室
